{
    "sourceFile": "src/components/ProjectStats.jsx",
    "activeCommit": 0,
    "commits": [
        {
            "activePatchIndex": 9,
            "patches": [
                {
                    "date": 1736966138127,
                    "content": "Index: \n===================================================================\n--- \n+++ \n"
                },
                {
                    "date": 1736966144492,
                    "content": "Index: \n===================================================================\n--- \n+++ \n@@ -1,1 +1,97 @@\n-ProjectStats\n\\ No newline at end of file\n+import React from 'react';\n+import { ArrowUp } from 'lucide-react';\n+\n+const StatCard = ({ value, label, prefix, suffix }) => (\n+  <div className=\"p-6\">\n+    <div className=\"flex items-center space-x-1\">\n+      {prefix && <ArrowUp className=\"text-orange-500 w-4 h-4\" />}\n+      <span className=\"text-4xl font-bold text-gray-900\">{value}</span>\n+      {suffix && <span className=\"text-4xl font-bold text-gray-900\">{suffix}</span>}\n+    </div>\n+    <p className=\"mt-2 text-gray-600\">{label}</p>\n+  </div>\n+);\n+\n+const ProjectStats = () => {\n+  const stats = [\n+    {\n+      value: \"70k\",\n+      suffix: \"+\",\n+      label: \"customers equipped — from DIY to major construction firms\"\n+    },\n+    {\n+      value: \"35\",\n+      prefix: true,\n+      suffix: \"%\",\n+      label: \"uptick in project efficiency with ScrewFast tools and services\"\n+    },\n+    {\n+      value: \"15.3\",\n+      prefix: true,\n+      suffix: \"%\",\n+      label: \"reduction in maintenance costs reported by long-term clients\"\n+    },\n+    {\n+      value: \"2\",\n+      suffix: \"x\",\n+      label: \"quicker assembly using innovative fastening solutions\"\n+    }\n+  ];\n+\n+  return (\n+    <div className=\"max-w-7xl mx-auto px-4 py-16 bg-gray-50\">\n+      <div className=\"grid grid-cols-1 lg:grid-cols-2 gap-8\">\n+        {/* Left side - Testimonial */}\n+        <div className=\"space-y-6 p-6\">\n+          <h2 className=\"text-3xl font-bold text-gray-900\">\n+            Fast-Track Your Projects\n+          </h2>\n+          <p className=\"text-gray-600\">\n+            At ScrewFast, we ensure a swift start with instant account setup.\n+            Experience the speed of construction redefined.\n+          </p>\n+          \n+          <blockquote className=\"mt-8\">\n+            <p className=\"text-xl italic text-gray-700\">\n+              \"ScrewFast dramatically boosted our project efficiency.\n+              Setup was instant, and their rapid response times are\n+              phenomenal. Truly a game-changer in hardware and\n+              construction support!\"\n+            </p>\n+            \n+            <div className=\"mt-4 flex items-center space-x-3\">\n+              <div className=\"w-12 h-12 rounded-full bg-gray-200 flex items-center justify-center\">\n+                <img \n+                  src=\"/api/placeholder/48/48\" \n+                  alt=\"Profile\" \n+                  className=\"rounded-full\"\n+                />\n+              </div>\n+              <div>\n+                <p className=\"font-semibold text-gray-900\">Samantha Ruiz</p>\n+                <p className=\"text-gray-600 text-sm\">\n+                  Chief Operating Officer | ConstructIt Inc.\n+                </p>\n+              </div>\n+            </div>\n+          </blockquote>\n+        </div>\n+\n+        {/* Right side - Stats Grid */}\n+        <div className=\"grid grid-cols-2 gap-4\">\n+          {stats.map((stat, index) => (\n+            <StatCard\n+              key={index}\n+              value={stat.value}\n+              label={stat.label}\n+              prefix={stat.prefix}\n+              suffix={stat.suffix}\n+            />\n+          ))}\n+        </div>\n+      </div>\n+    </div>\n+  );\n+};\n+\n+export default ProjectStats;\n\\ No newline at end of file\n"
                },
                {
                    "date": 1736966177981,
                    "content": "Index: \n===================================================================\n--- \n+++ \n@@ -1,5 +1,6 @@\n import React from 'react';\n+import PropTypes from 'prop-types';\n import { ArrowUp } from 'lucide-react';\n \n const StatCard = ({ value, label, prefix, suffix }) => (\n   <div className=\"p-6\">\n@@ -11,8 +12,20 @@\n     <p className=\"mt-2 text-gray-600\">{label}</p>\n   </div>\n );\n \n+StatCard.propTypes = {\n+  value: PropTypes.string.isRequired,\n+  label: PropTypes.string.isRequired,\n+  prefix: PropTypes.bool,\n+  suffix: PropTypes.string\n+};\n+\n+StatCard.defaultProps = {\n+  prefix: false,\n+  suffix: ''\n+};\n+\n const ProjectStats = () => {\n   const stats = [\n     {\n       value: \"70k\",\n"
                },
                {
                    "date": 1736966188237,
                    "content": "Index: \n===================================================================\n--- \n+++ \n@@ -1,5 +1,5 @@\n-import React from 'react';\n+\n import PropTypes from 'prop-types';\n import { ArrowUp } from 'lucide-react';\n \n const StatCard = ({ value, label, prefix, suffix }) => (\n@@ -68,9 +68,9 @@\n             <p className=\"text-xl italic text-gray-700\">\n               \"ScrewFast dramatically boosted our project efficiency.\n               Setup was instant, and their rapid response times are\n               phenomenal. Truly a game-changer in hardware and\n-              construction support!\"\n+              construction support!\n             </p>\n             \n             <div className=\"mt-4 flex items-center space-x-3\">\n               <div className=\"w-12 h-12 rounded-full bg-gray-200 flex items-center justify-center\">\n"
                },
                {
                    "date": 1736966321921,
                    "content": "Index: \n===================================================================\n--- \n+++ \n@@ -65,18 +65,18 @@\n           </p>\n           \n           <blockquote className=\"mt-8\">\n             <p className=\"text-xl italic text-gray-700\">\n-              \"ScrewFast dramatically boosted our project efficiency.\n+              ScrewFast dramatically boosted our project efficiency.\n               Setup was instant, and their rapid response times are\n               phenomenal. Truly a game-changer in hardware and\n               construction support!\n             </p>\n             \n             <div className=\"mt-4 flex items-center space-x-3\">\n               <div className=\"w-12 h-12 rounded-full bg-gray-200 flex items-center justify-center\">\n                 <img \n-                  src=\"/api/placeholder/48/48\" \n+                  src=\"https://plus.unsplash.com/premium_photo-1668485968590-aff3717c1dbe?w=800&auto=format&fit=crop&q=60&ixlib=rb-4.0.3&ixid=M3wxMjA3fDB8MHxzZWFyY2h8MTN8fHJhdyUyMHBvcnRyYWl0fGVufDB8fDB8fHww\" \n                   alt=\"Profile\" \n                   className=\"rounded-full\"\n                 />\n               </div>\n"
                },
                {
                    "date": 1736966336633,
                    "content": "Index: \n===================================================================\n--- \n+++ \n@@ -72,9 +72,9 @@\n               construction support!\n             </p>\n             \n             <div className=\"mt-4 flex items-center space-x-3\">\n-              <div className=\"w-12 h-12 rounded-full bg-gray-200 flex items-center justify-center\">\n+              <div className=\"w-6 h-12 rounded-full bg-gray-200 flex items-center justify-center\">\n                 <img \n                   src=\"https://plus.unsplash.com/premium_photo-1668485968590-aff3717c1dbe?w=800&auto=format&fit=crop&q=60&ixlib=rb-4.0.3&ixid=M3wxMjA3fDB8MHxzZWFyY2h8MTN8fHJhdyUyMHBvcnRyYWl0fGVufDB8fDB8fHww\" \n                   alt=\"Profile\" \n                   className=\"rounded-full\"\n"
                },
                {
                    "date": 1736966348242,
                    "content": "Index: \n===================================================================\n--- \n+++ \n@@ -72,9 +72,9 @@\n               construction support!\n             </p>\n             \n             <div className=\"mt-4 flex items-center space-x-3\">\n-              <div className=\"w-6 h-12 rounded-full bg-gray-200 flex items-center justify-center\">\n+              <div className=\"w-12 h-6 rounded-full bg-gray-200 flex items-center justify-center\">\n                 <img \n                   src=\"https://plus.unsplash.com/premium_photo-1668485968590-aff3717c1dbe?w=800&auto=format&fit=crop&q=60&ixlib=rb-4.0.3&ixid=M3wxMjA3fDB8MHxzZWFyY2h8MTN8fHJhdyUyMHBvcnRyYWl0fGVufDB8fDB8fHww\" \n                   alt=\"Profile\" \n                   className=\"rounded-full\"\n"
                },
                {
                    "date": 1736966354764,
                    "content": "Index: \n===================================================================\n--- \n+++ \n@@ -72,9 +72,9 @@\n               construction support!\n             </p>\n             \n             <div className=\"mt-4 flex items-center space-x-3\">\n-              <div className=\"w-12 h-6 rounded-full bg-gray-200 flex items-center justify-center\">\n+              <div className=\"w-6 h-6 rounded-full bg-gray-200 flex items-center justify-center\">\n                 <img \n                   src=\"https://plus.unsplash.com/premium_photo-1668485968590-aff3717c1dbe?w=800&auto=format&fit=crop&q=60&ixlib=rb-4.0.3&ixid=M3wxMjA3fDB8MHxzZWFyY2h8MTN8fHJhdyUyMHBvcnRyYWl0fGVufDB8fDB8fHww\" \n                   alt=\"Profile\" \n                   className=\"rounded-full\"\n"
                },
                {
                    "date": 1736966464474,
                    "content": "Index: \n===================================================================\n--- \n+++ \n@@ -51,9 +51,9 @@\n     }\n   ];\n \n   return (\n-    <div className=\"max-w-7xl mx-auto px-4 py-16 bg-gray-50\">\n+    <div className=\"max-w-full mx-auto px-4 py-16 bg-gray-50\">\n       <div className=\"grid grid-cols-1 lg:grid-cols-2 gap-8\">\n         {/* Left side - Testimonial */}\n         <div className=\"space-y-6 p-6\">\n           <h2 className=\"text-3xl font-bold text-gray-900\">\n"
                },
                {
                    "date": 1736966470198,
                    "content": "Index: \n===================================================================\n--- \n+++ \n@@ -51,9 +51,9 @@\n     }\n   ];\n \n   return (\n-    <div className=\"max-w-full mx-auto px-4 py-16 bg-gray-50\">\n+    <div className=\"max-w-7xl mx-auto px-4 py-16 bg-gray-50\">\n       <div className=\"grid grid-cols-1 lg:grid-cols-2 gap-8\">\n         {/* Left side - Testimonial */}\n         <div className=\"space-y-6 p-6\">\n           <h2 className=\"text-3xl font-bold text-gray-900\">\n"
                }
            ],
            "date": 1736966138126,
            "name": "Commit-0",
            "content": "ProjectStats"
        }
    ]
}